[
  {
    "orderNumber": "1",
    "price": "$35.31",
    "productName": "SanDisk 256GB Extreme microSDXC UHS-I Memory Card with Adapter - Up to 160MB/s, C10, U3, V30, 4K, A2, Micro SD - SDSQXA1-256G-GN6MA",
    "image": "https://m.media-amazon.com/images/I/81o+KgHuhxL._AC_SX679_.jpg",
    "deliverDate": "March 30, 2022",
    "orderDate": "March 30, 2022",
    "shipTo": "Home"
  },
  {
    "orderNumber": "11",
    "price": "$20.18",
    "productName": "SANFERGE Ceramic Flower Vase for Home Décor Office Decoration, 8 Inch, Black Gradient 2",
    "image": "https://m.media-amazon.com/images/I/418eKgY1FVS._SS284_.jpg",
    "deliverDate": "February 18, 2022",
    "orderDate": "February 16, 2022",
    "shipTo": "Home"
  },
  {
    "orderNumber": "111",
    "price": "$18.05",
    "productName": "MICHELANGELO 2 Quart Saucepan with Lid,Nonstick Sauce Pan with Lid, Small Pot with Lid, Stone Coating Sauce pan 2quart, 2 Quart Small Sauce Pan, Ergonomic Bakelite Handle, Black",
    "image": "https://m.media-amazon.com/images/I/512xP1alCYL._SS284_.jpg",
    "deliverDate": "January 28, 2022",
    "orderDate": "January 26, 2022",
    "shipTo": "Home"
  },
  {
    "orderNumber": "1111",
    "price": "$18.05",
    "productName": "USB C Hub, QGeeM 4-in-1 USB C Adapter with 4K USB C to HDMI Hub,100W Power Delivery,USB 3.0,Thunderbolt 3 Multiport Hub Compatible with MacBook Pro, X",
    "image": "https://m.media-amazon.com/images/I/310hL3xty0L._SS284_.jpg",
    "deliverDate": "January 16, 2022",
    "orderDate": "January 14, 2022",
    "shipTo": "Home"
  },
  {
    "orderNumber": "11111",
    "price": "$9.99",
    "productName": "HotHands Insole Foot Warmers With Adhesive Value Pack (5-Pairs)",
    "image": "https://images-na.ssl-images-amazon.com/images/I/51naDBqywEL._SY180_.jpg",
    "deliverDate": "Jan 15, 2022",
    "orderDate": "January 11, 2022",
    "shipTo": "Home"
  }
]